README.txt
setup.py
autobot/__init__.py
autobot/config.py
autobot/template.py
autobot.egg-info/PKG-INFO
autobot.egg-info/SOURCES.txt
autobot.egg-info/dependency_links.txt
autobot.egg-info/entry_points.txt
autobot.egg-info/not-zip-safe
autobot.egg-info/requires.txt
autobot.egg-info/top_level.txt
autobot/changes/__init__.py
autobot/changes/poller.py
autobot/process/__init__.py
autobot/process/factory.py
autobot/projects/__init__.py
autobot/projects/autobot/__init__.py
autobot/projects/toolbox/__init__.py
autobot/steps/__init__.py
autobot/steps/firefox.py
autobot/steps/virtualenv.py