Metadata-Version: 1.0
Name: autobot
Version: 0.1.1
Summary: buildbot front-end incarnation
Home-page: http://k0s.org/hg/autobot
Author: Jeff Hammel
Author-email: k0scist@gmail.com
License: MPL
Keywords: buildbot automation
Platform: UNKNOWN
